ayt_api/__init__.py
ayt_api/api.py
ayt_api/enums.py
ayt_api/exceptions.py
ayt_api/filters.py
ayt_api/types.py
ayt_api/utils.py
ayt_api-0.4.0.dist-info/LICENSE.md
ayt_api-0.4.0.dist-info/METADATA
ayt_api-0.4.0.dist-info/WHEEL
ayt_api-0.4.0.dist-info/top_level.txt
ayt_api-0.4.0.dist-info/RECORD
