Metadata-Version: 2.1
Name: ayt-api
Version: 0.4.0
Summary: A basic, asynchronous, object-oriented YouTube API wrapper written in Python.
Home-page: https://github.com/Revnoplex/ayt-api
Author: Revnoplex
Author-email: Revnoplex <revnoplex.business@protonmail.com>
License: # MIT License
Project-URL: Homepage, https://ayt-api.revnoplex.xyz
Project-URL: Repository, https://github.com/Revnoplex/ayt-api
Project-URL: Bug Tracker, https://github.com/Revnoplex/ayt-api/issues
Project-URL: Changelog, https://github.com/Revnoplex/ayt-api/blob/main/CHANGELOG.md
Project-URL: Documentation, https://ayt-api-docs.revnoplex.xyz
Keywords: api,youtube,async,asyncio,aiohttp,object-oriented,object oriented,youtube api,youtube-api,wrapper,youtube api wrapper,youtube-api-wrapper,api wrapper,api-wrapper,wrapper-api,wrapper api,wrapper library,wrapper-library
Classifier: Intended Audience :: Developers
Classifier: Natural Language :: English
Classifier: Operating System :: OS Independent
Classifier: Programming Language :: Python :: 3.9
Classifier: Programming Language :: Python :: 3.10
Classifier: Programming Language :: Python :: 3.11
Classifier: Programming Language :: Python :: 3.12
Classifier: Programming Language :: Python :: 3.13
Classifier: Topic :: Internet
Classifier: Topic :: Software Development :: Libraries
Classifier: Topic :: Software Development :: Libraries :: Python Modules
Classifier: Topic :: Utilities
Classifier: License :: OSI Approved :: MIT License
Classifier: Operating System :: OS Independent
Requires-Python: >=3.9.0
License-File: LICENSE.md
Requires-Dist: aiohttp>=3.8.1
Requires-Dist: wheel>=0.37.1
Requires-Dist: isodate>=0.6.1
Requires-Dist: setuptools>=62.3.2
